hashemcolorful/__init__.py
hashemcolorful/hashemcolorful.py
hashemcolorful-0.1.0.dist-info/METADATA
hashemcolorful-0.1.0.dist-info/WHEEL
hashemcolorful-0.1.0.dist-info/top_level.txt
hashemcolorful-0.1.0.dist-info/RECORD
