Metadata-Version: 2.4
Name: hashemcolorful
Version: 0.1.0
Summary: Simple color helpers built on colorama
Author: Hashem Allaham
Requires-Python: >=3.8
Requires-Dist: colorama
